linkchecker_tryer
