Metadata-Version: 1.1
Name: linkchecker-tryer
Version: 0.2.11
Summary: A tool for retrying linkchecker
Home-page: https://github.com/terryyin/linkchecker-tryer
Author: Terry Yin
Author-email: terry@odd-e.com
License: MIT
Download-URL: https://pypi.python.org/linkcheck-retryer/
Platform: any
Classifier: Development Status :: 5 - Production/Stable
Classifier: Intended Audience :: Developers
Classifier: Intended Audience :: End Users/Desktop
Classifier: License :: Freeware
Classifier: Operating System :: POSIX
Classifier: Operating System :: Microsoft :: Windows
Classifier: Operating System :: MacOS :: MacOS X
Classifier: Topic :: Software Development :: Quality Assurance
Classifier: Programming Language :: Python
Classifier: Programming Language :: Python :: 2.7
Classifier: Programming Language :: Python :: 3.2
Classifier: Programming Language :: Python :: 3.3
